json_key_press/__init__.py
json_key_press/key_press.py
json_key_press-2.0.dist-info/DESCRIPTION.rst
json_key_press-2.0.dist-info/METADATA
json_key_press-2.0.dist-info/RECORD
json_key_press-2.0.dist-info/WHEEL
json_key_press-2.0.dist-info/metadata.json
json_key_press-2.0.dist-info/top_level.txt
